re_helpers/__init__.py
re_helpers/binmerge.py
re_helpers-0.1.1.dist-info/entry_points.txt
re_helpers-0.1.1.dist-info/LICENSE
re_helpers-0.1.1.dist-info/WHEEL
re_helpers-0.1.1.dist-info/METADATA
re_helpers-0.1.1.dist-info/RECORD
